experiment_automator/__init__.py
experiment_automator/config.py
experiment_automator/constants.py
experiment_automator/csv_reporter.py
experiment_automator/db_storage.py
experiment_automator/dropbox_storage.py
experiment_automator/exceptions.py
experiment_automator/experiment_automator.py
experiment_automator/google_drive_storage.py
experiment_automator/image_uploader.py
experiment_automator/oauth_client.py
experiment_automator/result_container.py
experiment_automator/slack_notifier.py
experiment_automator/utils.py
experiment_automator-0.0.5.dist-info/LICENSE
experiment_automator-0.0.5.dist-info/METADATA
experiment_automator-0.0.5.dist-info/WHEEL
experiment_automator-0.0.5.dist-info/top_level.txt
experiment_automator-0.0.5.dist-info/RECORD
