Metadata-Version: 2.1
Name: experiment-automator
Version: 0.0.5
Summary: Experiment automator for ML
Home-page: https://github.com/mpolatcan/experiment-automator
Author: Mutlu Polatcan
Author-email: mutlupolatcan@gmail.com
License: UNKNOWN
Platform: UNKNOWN
Classifier: Programming Language :: Python :: 3
Classifier: License :: OSI Approved :: Apache Software License
Classifier: Operating System :: OS Independent
Requires-Dist: matplotlib
Requires-Dist: pyyaml
Requires-Dist: numpy
Requires-Dist: requests
Requires-Dist: requests-oauthlib
Requires-Dist: pymongo
